picklejar.py
picklejar-4.2.0.dist-info/METADATA
picklejar-4.2.0.dist-info/WHEEL
picklejar-4.2.0.dist-info/licenses/LICENSE
picklejar-4.2.0.dist-info/licenses/LICENSE.lesser
picklejar-4.2.0.dist-info/RECORD
