Metadata-Version: 2.4
Name: picklejar
Version: 4.2.0
Summary: Read and write pickles to a single file
Project-URL: Homepage, http://picklejar.readthedocs.io/
Project-URL: Repository, https://github.com/isaiah1112/picklejar
Author-email: Jesse Almanrode <jesse@almanrode.com>
License-Expression: LGPL-3.0-or-later
License-File: LICENSE
License-File: LICENSE.lesser
Classifier: Development Status :: 5 - Production/Stable
Classifier: Intended Audience :: Developers
Classifier: License :: OSI Approved :: GNU Lesser General Public License v3 or later (LGPLv3+)
Classifier: Programming Language :: Python
Classifier: Programming Language :: Python :: 3.10
Classifier: Programming Language :: Python :: 3.11
Classifier: Programming Language :: Python :: 3.12
Classifier: Programming Language :: Python :: 3.13
Classifier: Programming Language :: Python :: 3.14
Classifier: Topic :: Software Development :: Libraries
Classifier: Topic :: Software Development :: Libraries :: Python Modules
Requires-Python: <4.0,>3.10
Requires-Dist: dill<0.4,>=0.3
